[{"medal":"Bronze","beer":"DD Blonde","brewery":"Hop Valley Brewing Co.","style":"American-Style Wheat Beer","year":2012,"comp":"WBC"},{"medal":"Silver","beer":"1919 choc beer","brewery":"choc Beer Co.","style":"American-Style Wheat Beer","year":2012,"comp":"WBC"},{"medal":"Gold","beer":"Wagon Box Wheat","brewery":"Black Tooth Brewing Co.","style":"American-Style Wheat Beer","year":2012,"comp":"WBC"},{"medal":"Bronze","beer":"Leavenworth Boulder Bend Dunkelweizen","brewery":"Fish Brewing Co.","style":"American-Style Wheat Beer With Yeast","year":2012,"comp":"WBC"},{"medal":"Silver","beer":"Miners Gold","brewery":"Lewis & Clark Brewing Co.","style":"American-Style Wheat Beer With Yeast","year":2012,"comp":"WBC"},{"medal":"Gold","beer":"Whitetail Wheat","brewery":"Montana Brewing Co.","style":"American-Style Wheat Beer With Yeast","year":2012,"comp":"WBC"},{"medal":"Bronze","beer":"Blushing Monk","brewery":"Founders Brewing Co.","style":"Fruit Beer","year":2012,"comp":"WBC"},{"medal":"Silver","beer":"Da Yoopers","brewery":"Rocky Mountain Brewery","style":"Fruit Beer","year":2012,"comp":"WBC"},{"medal":"Gold","beer":"Eat A Peach","brewery":"Rocky Mountain Brewery","style":"Fruit Beer","year":2012,"comp":"WBC"},{"medal":"Bronze","beer":"Amsterdam Framboise","brewery":"Amsterdam Brewing Co.","style":"Fruit Wheat Beer","year":2012,"comp":"WBC"},{"medal":"Silver","beer":"Blue Moon Vintage Blonde Ale","brewery":"Blue Moon Brewing Co.","style":"Fruit Wheat Beer","year":2012,"comp":"WBC"},{"medal":"Gold","beer":"Minoh Beer YUZU-WHITE-ALE","brewery":"A_J_I Beer","style":"Fruit Wheat Beer","year":2012,"comp":"WBC"},{"medal":"Bronze","beer":"The Great Pumpkin","brewery":"Elysian Brewing Co.","style":"Field Beer or Pumpkin Beer","year":2012,"comp":"WBC"},{"medal":"Silver","beer":"Saint Arnold Pumpkinator","brewery":"Saint Arnold Brewing Co.","style":"Field Beer or Pumpkin Beer","year":2012,"comp":"WBC"},{"medal":"Gold","beer":"Turnip the Beets","brewery":"Bull & Bush Brewery","style":"Field Beer or Pumpkin Beer","year":2012,"comp":"WBC"},{"medal":"Bronze","beer":"Hardywood Gingerbread Stout","brewery":"Hardywood Park Craft Brewery","style":"Herb and Spice Beer","year":2012,"comp":"WBC"},{"medal":"Silver","beer":"Ring Of Fire","brewery":"Dragonmead Microbrewery","style":"Herb and Spice Beer","year":2012,"comp":"WBC"},{"medal":"Gold","beer":"Sgt. Pepper","brewery":"Cambridge Brewing Co.","style":"Herb and Spice Beer","year":2012,"comp":"WBC"},{"medal":"Bronze","beer":"Odin's Raven","brewery":"Alpine Beer Co.","style":"Chocolate Beer","year":2012,"comp":"WBC"},{"medal":"Silver","beer":"X-1 Chocolate Imperial Rye Porter","brewery":"DuClaw Brewing Co.","style":"Chocolate Beer","year":2012,"comp":"WBC"},{"medal":"Gold","beer":"H\u00e1zmela Rusa","brewery":"La Chingoner\u00eda","style":"Chocolate Beer","year":2012,"comp":"WBC"},{"medal":"Bronze","beer":"Coffee Stout","brewery":"Rock Bottom Arlington","style":"Coffee Beer","year":2012,"comp":"WBC"},{"medal":"Silver","beer":"Drunken Elf Stout","brewery":"Columbia River Brewing Co.","style":"Coffee Beer","year":2012,"comp":"WBC"},{"medal":"Gold","beer":"Bacon and Eggs Breakfast Coffee Imperial Porter","brewery":"Pizza Port Ocean Beach","style":"Coffee Beer","year":2012,"comp":"WBC"},{"medal":"Bronze","beer":"Donner Party Porter","brewery":"FiftyFifty Brewing Co.","style":"Specialty Beer","year":2012,"comp":"WBC"},{"medal":"Silver","beer":"Maple Tripple","brewery":"Lawson's Finest Liquids","style":"Specialty Beer","year":2012,"comp":"WBC"},{"medal":"Gold","beer":"Hangar 24 Winter Warmer","brewery":"Hangar 24 Craft Brewery","style":"Specialty Beer","year":2012,"comp":"WBC"},{"medal":"Bronze","beer":"Jopen Jacobus RPA","brewery":"Jopenkerk Bierbrouwerij","style":"Rye Beer","year":2012,"comp":"WBC"},{"medal":"Silver","beer":"3 Flowers IPA","brewery":"Marin Brewing Co.","style":"Rye Beer","year":2012,"comp":"WBC"},{"medal":"Gold","beer":"Ruthless Rye IPA","brewery":"Sierra Nevada Brewing Co.","style":"Rye Beer","year":2012,"comp":"WBC"},{"medal":"Bronze","beer":"Killer Bee","brewery":"Dragonmead Microbrewery","style":"Specialty Honey Beer","year":2012,"comp":"WBC"},{"medal":"Silver","beer":"M\u00e9nage a Trois Braggot","brewery":"Crabtree Brewing Co.","style":"Specialty Honey Beer","year":2012,"comp":"WBC"},{"medal":"Gold","beer":"Bor\u00e9ale Dor\u00e9e","brewery":"Les Brasseurs du Nord","style":"Specialty Honey Beer","year":2012,"comp":"WBC"},{"medal":"Bronze","beer":"Revelations Stout","brewery":"The Public House Brewing Co.","style":"Session Beer","year":2012,"comp":"WBC"},{"medal":"Silver","beer":"Kellerweis","brewery":"Sierra Nevada Brewing Co.","style":"Session Beer","year":2012,"comp":"WBC"},{"medal":"Gold","beer":"Vienna Lager","brewery":"Squatters Pub Brewery","style":"Session Beer","year":2012,"comp":"WBC"},{"medal":"Bronze","beer":"Double Pilsner","brewery":"Odell Brewing Co.","style":"Other Strong Beer","year":2012,"comp":"WBC"},{"medal":"Silver","beer":"Imperial Cream Ale","brewery":"Nexus Brewery","style":"Other Strong Beer","year":2012,"comp":"WBC"},{"medal":"Gold","beer":"Star Brew","brewery":"Marin Brewing Co.","style":"Other Strong Beer","year":2012,"comp":"WBC"},{"medal":"Bronze","beer":"Where There's Smoke...","brewery":"Manzanita Brewing Co.","style":"Experimental Beer","year":2012,"comp":"WBC"},{"medal":"Silver","beer":"Noble Rot","brewery":"Dogfish Head Craft Brewery","style":"Experimental Beer","year":2012,"comp":"WBC"},{"medal":"Gold","beer":"Petit Obscura","brewery":"Telegraph Brewing Co.","style":"Experimental Beer","year":2012,"comp":"WBC"},{"medal":"Bronze","beer":"Oyster Stout","brewery":"Upright Brewing Co.","style":"Indigenous Beer","year":2012,"comp":"WBC"},{"medal":"Silver","beer":"Hqt","brewery":"21st-Amendment Brewery","style":"Indigenous Beer","year":2012,"comp":"WBC"},{"medal":"Gold","beer":"Got Beer","brewery":"BJ's Restaurant & Brewery - Tacoma","style":"Indigenous Beer","year":2012,"comp":"WBC"},{"medal":"Bronze","beer":"Glutenberg Blonde","brewery":"Brasseurs Sans Gluten","style":"Gluten-Free Beer","year":2012,"comp":"WBC"},{"medal":"Silver","beer":"Glutenberg Pale Ale","brewery":"Brasseurs Sans Gluten","style":"Gluten-Free Beer","year":2012,"comp":"WBC"},{"medal":"Gold","beer":"Glutenberg Rousse","brewery":"Brasseurs Sans Gluten","style":"Gluten-Free Beer","year":2012,"comp":"WBC"},{"medal":"Bronze","beer":"Le Freak","brewery":"Green Flash Brewing Co.","style":"American-Belgo-Style Ale","year":2012,"comp":"WBC"},{"medal":"Silver","beer":"Blue Reserve","brewery":"Blue Mountain Brewery","style":"American-Belgo-Style Ale","year":2012,"comp":"WBC"},{"medal":"Gold","beer":"Last Chance","brewery":"The Haymarket Pub & Brewery","style":"American-Belgo-Style Ale","year":2012,"comp":"WBC"},{"medal":"Bronze","beer":"Supplication","brewery":"Russian River Brewing Co.","style":"American-Style Sour Ale","year":2012,"comp":"WBC"},{"medal":"Silver","beer":"Mattina Rossa","brewery":"Allagash Brewing Co.","style":"American-Style Sour Ale","year":2012,"comp":"WBC"},{"medal":"Gold","beer":"Ching Ching","brewery":"Bend Brewing Co.","style":"American-Style Sour Ale","year":2012,"comp":"WBC"},{"medal":"Bronze","beer":"Wild Wild Brett Rouge","brewery":"Crooked Stave Artisan Beer Project","style":"American-Style Brett Ale","year":2012,"comp":"WBC"},{"medal":"Silver","beer":"Peche","brewery":"AC Golden Brewing Co.","style":"American-Style Brett Ale","year":2012,"comp":"WBC"},{"medal":"Gold","beer":"Peche 'n Brett","brewery":"Logsdon Farmhouse Ales","style":"American-Style Brett Ale","year":2012,"comp":"WBC"},{"medal":"Bronze","beer":"Central City Oaked Porter","brewery":"Central City Brewing Co.","style":"Wood- and Barrel-Aged Beer","year":2012,"comp":"WBC"},{"medal":"Silver","beer":"Brandy Barrel Abbey Normal","brewery":"Fox River Brewing Co.","style":"Wood- and Barrel-Aged Beer","year":2012,"comp":"WBC"},{"medal":"Gold","beer":"Sarah's Two Headed Buffalo","brewery":"Rock Bottom Cincinnati","style":"Wood- and Barrel-Aged Beer","year":2012,"comp":"WBC"},{"medal":"Bronze","beer":"Bourbon Abominable Winter Ale","brewery":"Fremont Brewing Co.","style":"Wood- and Barrel-Aged Strong Beer","year":2012,"comp":"WBC"},{"medal":"Silver","beer":"King Henry","brewery":"Goose Island Beer Co.","style":"Wood- and Barrel-Aged Strong Beer","year":2012,"comp":"WBC"},{"medal":"Gold","beer":"Samuel Adams Utopias 2011","brewery":"The Boston Beer Co.","style":"Wood- and Barrel-Aged Strong Beer","year":2012,"comp":"WBC"},{"medal":"Bronze","beer":"The Event Horizon","brewery":"Olde Hickory Brewery","style":"Wood- and Barrel-Aged Strong Stout","year":2012,"comp":"WBC"},{"medal":"Silver","beer":"Great Grandfather Raven","brewery":"Black Raven Brewing Co.","style":"Wood- and Barrel-Aged Strong Stout","year":2012,"comp":"WBC"},{"medal":"Gold","beer":"Barrel Aged BORIS The Crusher Oatmeal-Imperial Stout","brewery":"Hoppin' Frog Brewing Co.","style":"Wood- and Barrel-Aged Strong Stout","year":2012,"comp":"WBC"},{"medal":"Bronze","beer":"Melange #1","brewery":"The Bruery","style":"Wood- and Barrel-Aged Sour Beer","year":2012,"comp":"WBC"},{"medal":"Silver","beer":"Le Serpent Cerise","brewery":"Snake River Brewing Co.","style":"Wood- and Barrel-Aged Sour Beer","year":2012,"comp":"WBC"},{"medal":"Gold","beer":"Lovibonds Sour Grapes","brewery":"Lovibonds Brewery","style":"Wood- and Barrel-Aged Sour Beer","year":2012,"comp":"WBC"},{"medal":"Bronze","beer":"Release the Hounds Barley Wine Vintage 1999","brewery":"Bull & Bush Brewery","style":"Aged Beer","year":2012,"comp":"WBC"},{"medal":"Silver","beer":"Vintage Horn Dog","brewery":"Flying Dog Brewery","style":"Aged Beer","year":2012,"comp":"WBC"},{"medal":"Gold","beer":"Samichlaus \"2004\"","brewery":"Brauerei Schloss Eggenberg","style":"Aged Beer","year":2012,"comp":"WBC"},{"medal":"Bronze","beer":"5 O'Clock Shadow","brewery":"Grand Teton Brewing Co.","style":"Kellerbier\/Zwickelbier","year":2012,"comp":"WBC"},{"medal":"Silver","beer":"VI\u00c6MILIA","brewery":"Birrificio del Ducato","style":"Kellerbier\/Zwickelbier","year":2012,"comp":"WBC"},{"medal":"Gold","beer":"Ketterer Zwickel Pils","brewery":"Familienbrauerei M. Ketterer","style":"Kellerbier\/Zwickelbier","year":2012,"comp":"WBC"},{"medal":"Bronze","beer":"Grodzinski","brewery":"Iron Hill Brewery & Restaurant - Newark","style":"Smoke Beer","year":2012,"comp":"WBC"},{"medal":"Silver","beer":"BraufactuM Roog","brewery":"Die Internationale Brau-Manufacturen","style":"Smoke Beer","year":2012,"comp":"WBC"},{"medal":"Gold","beer":"Fujizakura Kogen Beer Rauch","brewery":"Fujizakura Kogen Beer","style":"Smoke Beer","year":2012,"comp":"WBC"},{"medal":"Bronze","beer":"Norte Blanca","brewery":"Cervecer\u00eda y Malter\u00eda Quilmes","style":"Australasian, Latin American or Tropical-Style Light Lager","year":2012,"comp":"WBC"},{"medal":"Silver","beer":"Anchor Ice","brewery":"Hainan Asia Pacific Brewery Co.","style":"Australasian, Latin American or Tropical-Style Light Lager","year":2012,"comp":"WBC"},{"medal":"Gold","beer":"Quilmes Cristal","brewery":"Cervecer\u00eda y Malter\u00eda Quilmes","style":"Australasian, Latin American or Tropical-Style Light Lager","year":2012,"comp":"WBC"},{"medal":"Bronze","beer":"Birra Moretti","brewery":"Heineken Italia","style":"International-Style Lager","year":2012,"comp":"WBC"},{"medal":"Silver","beer":"Cisk Export Premium Lager","brewery":"Simonds Farsons Cisk","style":"International-Style Lager","year":2012,"comp":"WBC"},{"medal":"Gold","beer":"Pace\u00f1a Pico de Oro","brewery":"Cervecer\u00eda Boliviana Nacional","style":"International-Style Lager","year":2012,"comp":"WBC"},{"medal":"Bronze","beer":"Dan - My Turn Series","brewery":"Lakefront Brewery","style":"Baltic-Style Porter","year":2012,"comp":"WBC"},{"medal":"Silver","beer":"Battle Axe Baltic Porter","brewery":"Fat Heads Brewery","style":"Baltic-Style Porter","year":2012,"comp":"WBC"},{"medal":"Gold","beer":"Baltic Gnome Porter","brewery":"Rock Bottom Denver","style":"Baltic-Style Porter","year":2012,"comp":"WBC"},{"medal":"Bronze","beer":"Hochdorfer Hopfen-Leicht","brewery":"Hochdorfer Kronenbrauerei Otto Haizmann","style":"European-Style Low-Alcohol Lager\/German-Style Leicht(bier)","year":2012,"comp":"WBC"},{"medal":"Silver","beer":"Beck's Premier Light","brewery":"Brauerei Beck & Co.","style":"European-Style Low-Alcohol Lager\/German-Style Leicht(bier)","year":2012,"comp":"WBC"},{"medal":"Bronze","beer":"Baumgartner Pils","brewery":"Brauerei Jos. Baumgartner","style":"German-Style Pilsener","year":2012,"comp":"WBC"},{"medal":"Silver","beer":"Sch\u00f6nramer Pils","brewery":"Private Landbrauerei Sch\u00f6nram","style":"German-Style Pilsener","year":2012,"comp":"WBC"},{"medal":"Gold","beer":"Brio","brewery":"Olgerdin Egill Skallagrimsson","style":"German-Style Pilsener","year":2012,"comp":"WBC"},{"medal":"Bronze","beer":"Gambrinus Premium","brewery":"Plze\u0148sk\u00fd Prazdroj a.s.","style":"Bohemian-Style Pilsener","year":2012,"comp":"WBC"},{"medal":"Silver","beer":"Kru_ovice Imperial","brewery":"Heineken","style":"Bohemian-Style Pilsener","year":2012,"comp":"WBC"},{"medal":"Gold","beer":"Starobrno Le_\u00e1k","brewery":"Heineken Czech Republic","style":"Bohemian-Style Pilsener","year":2012,"comp":"WBC"},{"medal":"Bronze","beer":"Helles","brewery":"Kitzmann Br\u00e4u","style":"M\u00fcnchner-Style Helles","year":2012,"comp":"WBC"},{"medal":"Silver","beer":"L\u00f6wenbr\u00e4u","brewery":"L\u00f6wenbr\u00e4u","style":"M\u00fcnchner-Style Helles","year":2012,"comp":"WBC"},{"medal":"Gold","beer":"Urtyp Hell","brewery":"L\u00f6wenbrauerei Passau","style":"M\u00fcnchner-Style Helles","year":2012,"comp":"WBC"},{"medal":"Bronze","beer":"Schlappeseppel Export","brewery":"Brauerei Schlappeseppel","style":"Dortmunder\/Export or German-Style Oktoberfest","year":2012,"comp":"WBC"},{"medal":"Silver","beer":"Tauras Tradicinis","brewery":"Kalnapilio-Tauro Grupe","style":"Dortmunder\/Export or German-Style Oktoberfest","year":2012,"comp":"WBC"},{"medal":"Gold","beer":"_vyturys Ekstra","brewery":"JSC _vyturys-Utenos Alus","style":"Dortmunder\/Export or German-Style Oktoberfest","year":2012,"comp":"WBC"},{"medal":"Bronze","beer":"Belle Gueule Originale","brewery":"Brasseurs RJ","style":"Vienna-Style Lager","year":2012,"comp":"WBC"},{"medal":"Silver","beer":"Heavy Seas Marzen Vienna Lager","brewery":"Clipper City Brewing Co.","style":"Vienna-Style Lager","year":2012,"comp":"WBC"},{"medal":"Gold","beer":"Vienna Lager","brewery":"Devils Backbone Brewing Co.","style":"Vienna-Style Lager","year":2012,"comp":"WBC"},{"medal":"Bronze","beer":"Ur-Saalfelder","brewery":"B\u00fcrgerliches Brauhaus Saalfeld","style":"German-Style M\u00e4rzen","year":2012,"comp":"WBC"},{"medal":"Silver","beer":"Rocktoberfest","brewery":"Rock Bottom Long Beach","style":"German-Style M\u00e4rzen","year":2012,"comp":"WBC"},{"medal":"Gold","beer":"Florhosen","brewery":"The SandLot","style":"German-Style M\u00e4rzen","year":2012,"comp":"WBC"},{"medal":"Bronze","beer":"Riegele Aechtes Dunkel","brewery":"Brauerei S. Riegele","style":"European-Style Dark\/M\u00fcnchner Dunkel","year":2012,"comp":"WBC"},{"medal":"Silver","beer":"King Dark Lager","brewery":"King Brewery","style":"European-Style Dark\/M\u00fcnchner Dunkel","year":2012,"comp":"WBC"},{"medal":"Gold","beer":"Weltenburger Kloster Barock Dunkel","brewery":"Klosterbrauerei Weltenburg","style":"European-Style Dark\/M\u00fcnchner Dunkel","year":2012,"comp":"WBC"},{"medal":"Bronze","beer":"Cameron's Dark 266","brewery":"Cameron's Brewing Co.","style":"German-Style Schwarzbier","year":2012,"comp":"WBC"},{"medal":"Silver","beer":"Point 2012 Black Ale","brewery":"Stevens Point Brewery","style":"German-Style Schwarzbier","year":2012,"comp":"WBC"},{"medal":"Gold","beer":"Art of Science Schwarzbier","brewery":"Dillon DAM Brewery","style":"German-Style Schwarzbier","year":2012,"comp":"WBC"},{"medal":"Bronze","beer":"Troegenator","brewery":"Tr\u00f6egs Brewing Co.","style":"Traditional German-Style Bock","year":2012,"comp":"WBC"},{"medal":"Silver","beer":"Winter Bock","brewery":"Silver City Brewery","style":"Traditional German-Style Bock","year":2012,"comp":"WBC"},{"medal":"Gold","beer":"Doppel-Hirsch","brewery":"Der Hirschbr\u00e4u","style":"Traditional German-Style Bock","year":2012,"comp":"WBC"},{"medal":"Bronze","beer":"Blonde Doppelbock","brewery":"Capital Brewery Co.","style":"German-Style Heller Bock\/Maibock","year":2012,"comp":"WBC"},{"medal":"Silver","beer":"Der Ulmer Maibock","brewery":"Familienbrauerei Bauh\u00f6fer","style":"German-Style Heller Bock\/Maibock","year":2012,"comp":"WBC"},{"medal":"Gold","beer":"Maibock","brewery":"Blind Tiger Brewery & Restaurant","style":"German-Style Heller Bock\/Maibock","year":2012,"comp":"WBC"},{"medal":"Bronze","beer":"Dominator Dopplebock","brewery":"Sun King Brewing Co.","style":"German-Style Doppelbock or Eisbock","year":2012,"comp":"WBC"},{"medal":"Silver","beer":"Hochdorfer Barbara Bock","brewery":"Hochdorfer Kronenbrauerei Otto Haizmann","style":"German-Style Doppelbock or Eisbock","year":2012,"comp":"WBC"},{"medal":"Gold","beer":"Holzfassgelagerter Eisbock","brewery":"Brauhaus Faust","style":"German-Style Doppelbock or Eisbock","year":2012,"comp":"WBC"},{"medal":"Bronze","beer":"Milwaukee's Best","brewery":"Miller Brewing Co.","style":"American-Style Cream Ale or Lager","year":2012,"comp":"WBC"},{"medal":"Silver","beer":"Old Style","brewery":"Pabst Brewing Co.","style":"American-Style Cream Ale or Lager","year":2012,"comp":"WBC"},{"medal":"Gold","beer":"Prestige","brewery":"Brasserie Nationale d'Haiti","style":"American-Style Cream Ale or Lager","year":2012,"comp":"WBC"},{"medal":"Bronze","beer":"Michelob Light","brewery":"Anheuser-Busch","style":"American-Style Lager or Light Lager","year":2012,"comp":"WBC"},{"medal":"Silver","beer":"Michelob Ultra","brewery":"Anheuser-Busch","style":"American-Style Lager or Light Lager","year":2012,"comp":"WBC"},{"medal":"Gold","beer":"Coors Light","brewery":"Coors Brewing Co.","style":"American-Style Lager or Light Lager","year":2012,"comp":"WBC"},{"medal":"Bronze","beer":"Icehouse","brewery":"Miller Brewing Co.","style":"American-Style Premium Lager or Specialty Lager","year":2012,"comp":"WBC"},{"medal":"Silver","beer":"Evans Original","brewery":"Cervecer\u00eda Mexicana","style":"American-Style Premium Lager or Specialty Lager","year":2012,"comp":"WBC"},{"medal":"Gold","beer":"Steel Reserve","brewery":"Miller Brewing Co.","style":"American-Style Premium Lager or Specialty Lager","year":2012,"comp":"WBC"},{"medal":"Bronze","beer":"Cali Common","brewery":"Lucky Hand Beer","style":"American-Style Amber Lager","year":2012,"comp":"WBC"},{"medal":"Silver","beer":"Colorado Native","brewery":"AC Golden Brewing Co.","style":"American-Style Amber Lager","year":2012,"comp":"WBC"},{"medal":"Gold","beer":"Winter Skal","brewery":"Capital Brewery Co.","style":"American-Style Amber Lager","year":2012,"comp":"WBC"},{"medal":"Bronze","beer":"Santo","brewery":"Saint Arnold Brewing Co.","style":"American-Style Dark Lager","year":2012,"comp":"WBC"},{"medal":"Silver","beer":"Shiner Bock","brewery":"The Spoetzl Brewery","style":"American-Style Dark Lager","year":2012,"comp":"WBC"},{"medal":"Gold","beer":"Leinenkugel's Creamy Dark","brewery":"Jacob Leinenkugel Brewing Co.","style":"American-Style Dark Lager","year":2012,"comp":"WBC"},{"medal":"Bronze","beer":"Benny's Pale Ale","brewery":"Shoreline Brewery","style":"Australasian-Style Pale Ale or International-Style Pale Ale","year":2012,"comp":"WBC"},{"medal":"Silver","beer":"Endeavour True Vintage 2011 Reserve Pale Ale","brewery":"Endeavour True Vintage Beer","style":"Australasian-Style Pale Ale or International-Style Pale Ale","year":2012,"comp":"WBC"},{"medal":"Gold","beer":"805 IPA","brewery":"Firestone Walker Brewing Co.","style":"Australasian-Style Pale Ale or International-Style Pale Ale","year":2012,"comp":"WBC"},{"medal":"Bronze","beer":"Point Three Kings","brewery":"Stevens Point Brewery","style":"German-Style K\u00f6lsch\/K\u00f6ln-Style K\u00f6lsch","year":2012,"comp":"WBC"},{"medal":"Silver","beer":"Chuckanut Kolsch","brewery":"Chuckanut Brewery","style":"German-Style K\u00f6lsch\/K\u00f6ln-Style K\u00f6lsch","year":2012,"comp":"WBC"},{"medal":"Gold","beer":"Sunbru","brewery":"Four Peaks Brewing Co.","style":"German-Style K\u00f6lsch\/K\u00f6ln-Style K\u00f6lsch","year":2012,"comp":"WBC"},{"medal":"Bronze","beer":"Real McCoy Amber","brewery":"Mammoth Brewing Co.","style":"German-Style Brown Ale\/D\u00fcsseldorf-Style Altbier","year":2012,"comp":"WBC"},{"medal":"Silver","beer":"Rhine Heights","brewery":"Vintage Brewing Co.","style":"German-Style Brown Ale\/D\u00fcsseldorf-Style Altbier","year":2012,"comp":"WBC"},{"medal":"Gold","beer":"Alt-eration","brewery":"Hops & Grain Brewing","style":"German-Style Brown Ale\/D\u00fcsseldorf-Style Altbier","year":2012,"comp":"WBC"},{"medal":"Bronze","beer":"Vitis Reductus Weisse","brewery":"Outer Banks Brewing Station","style":"German-Style Sour Ale","year":2012,"comp":"WBC"},{"medal":"Silver","beer":"Hottenroth Berliner Weisse","brewery":"The Bruery","style":"German-Style Sour Ale","year":2012,"comp":"WBC"},{"medal":"Gold","beer":"Berliner Weisse","brewery":"Steamworks Brewing Co.","style":"German-Style Sour Ale","year":2012,"comp":"WBC"},{"medal":"Bronze","beer":"Edelweiss Hefetr\u00fcb","brewery":"Brau Union \u00d6sterreich","style":"South German-Style Hefeweizen\/Hefeweissbier","year":2012,"comp":"WBC"},{"medal":"Silver","beer":"Baltika N\u00b08 Wheat","brewery":"Baltika Breweries","style":"South German-Style Hefeweizen\/Hefeweissbier","year":2012,"comp":"WBC"},{"medal":"Gold","beer":"HEF","brewery":"Burleigh Brewing Co.","style":"South German-Style Hefeweizen\/Hefeweissbier","year":2012,"comp":"WBC"},{"medal":"Bronze","beer":"Ketterer Ur-Weisse kristall","brewery":"Familienbrauerei M. Ketterer","style":"German-Style Pale Wheat Ale","year":2012,"comp":"WBC"},{"medal":"Silver","beer":"Gold Ochsen Kristallweizen","brewery":"Brauerei Gold Ochsen","style":"German-Style Pale Wheat Ale","year":2012,"comp":"WBC"},{"medal":"Gold","beer":"Boscos Hefeweizen","brewery":"Boscos Brewing Co.","style":"German-Style Pale Wheat Ale","year":2012,"comp":"WBC"},{"medal":"Bronze","beer":"Unertl Gourmet Weisse","brewery":"Wei\u00dfbr\u00e4u Unertl","style":"German-Style Dark Wheat Ale","year":2012,"comp":"WBC"},{"medal":"Silver","beer":"Schneider Weisse Original","brewery":"Weisses Br\u00e4euhaus G. Schneider & Sohn","style":"German-Style Dark Wheat Ale","year":2012,"comp":"WBC"},{"medal":"Gold","beer":"Brauerei Michael Plank Original Hefeweizen","brewery":"Brauerei Michael Plank","style":"German-Style Dark Wheat Ale","year":2012,"comp":"WBC"},{"medal":"Bronze","beer":"Rhaner Lilly Bock","brewery":"Rhanerbr\u00e4u","style":"South German-Style Weizenbock\/Weissbock","year":2012,"comp":"WBC"},{"medal":"Silver","beer":"Live Oak Primus","brewery":"Live Oak Brewing Co.","style":"South German-Style Weizenbock\/Weissbock","year":2012,"comp":"WBC"},{"medal":"Gold","beer":"Brauerei Michael Plank Heller Weizenbock","brewery":"Brauerei Michael Plank","style":"South German-Style Weizenbock\/Weissbock","year":2012,"comp":"WBC"},{"medal":"Bronze","beer":"La Perouse White","brewery":"Maui Brewing Co.","style":"Belgian-Style Witbier","year":2012,"comp":"WBC"},{"medal":"Silver","beer":"Hoegaarden","brewery":"Hoegaarden Brewery","style":"Belgian-Style Witbier","year":2012,"comp":"WBC"},{"medal":"Gold","beer":"Allagash White","brewery":"Allagash Brewing Co.","style":"Belgian-Style Witbier","year":2012,"comp":"WBC"},{"medal":"Bronze","beer":"Urban Farmhouse Ale","brewery":"The Commons Brewery","style":"French- & Belgian-Style Saison","year":2012,"comp":"WBC"},{"medal":"Silver","beer":"Saison Station 55","brewery":"Hopfenstark Brewery","style":"French- & Belgian-Style Saison","year":2012,"comp":"WBC"},{"medal":"Gold","beer":"Carnevale","brewery":"The Lost Abbey","style":"French- & Belgian-Style Saison","year":2012,"comp":"WBC"},{"medal":"Bronze","beer":"Gift of the Magi","brewery":"The Lost Abbey","style":"Belgian- and French-Style Ale","year":2012,"comp":"WBC"},{"medal":"Silver","beer":"Saison Noir","brewery":"Bastone Brewery","style":"Belgian- and French-Style Ale","year":2012,"comp":"WBC"},{"medal":"Gold","beer":"FSB Spring Brew","brewery":"Front Street Brewery","style":"Belgian- and French-Style Ale","year":2012,"comp":"WBC"},{"medal":"Bronze","beer":"Troubadour Blond","brewery":"Brouwerij The Musketeers","style":"Belgian-Style Blonde Ale or Pale Ale","year":2012,"comp":"WBC"},{"medal":"Silver","beer":"Leffe Blonde","brewery":"AB InBev","style":"Belgian-Style Blonde Ale or Pale Ale","year":2012,"comp":"WBC"},{"medal":"Gold","beer":"Ommegang Rare Vos","brewery":"Brewery Ommegang","style":"Belgian-Style Blonde Ale or Pale Ale","year":2012,"comp":"WBC"},{"medal":"Bronze","beer":"Fifth Element Vintage 2011","brewery":"Squatters Pub Brewery","style":"Belgian-Style Sour Ale","year":2012,"comp":"WBC"},{"medal":"Silver","beer":"Oude Kriek Oud Beersel","brewery":"Oud Beersel","style":"Belgian-Style Sour Ale","year":2012,"comp":"WBC"},{"medal":"Gold","beer":"Oude Geuze Boon","brewery":"Brouwerij Frank Boon","style":"Belgian-Style Sour Ale","year":2012,"comp":"WBC"},{"medal":"Bronze","beer":"Oud Jeremiah","brewery":"BJ's Restaurant & Brewery - Brea","style":"Belgian-Style Flanders Oud Bruin or Oud Red Ale","year":2012,"comp":"WBC"},{"medal":"Silver","beer":"Monomoy Kriek","brewery":"Cisco Brewers","style":"Belgian-Style Flanders Oud Bruin or Oud Red Ale","year":2012,"comp":"WBC"},{"medal":"Gold","beer":"Oude Tart","brewery":"The Bruery","style":"Belgian-Style Flanders Oud Bruin or Oud Red Ale","year":2012,"comp":"WBC"},{"medal":"Bronze","beer":"Ovila Dubbel","brewery":"Sierra Nevada Brewing Co.","style":"Belgian-Style Dubbel","year":2012,"comp":"WBC"},{"medal":"Silver","beer":"Belgian Dubbel","brewery":"Bier Brewery","style":"Belgian-Style Dubbel","year":2012,"comp":"WBC"},{"medal":"Gold","beer":"Leffe Brown","brewery":"AB InBev","style":"Belgian-Style Dubbel","year":2012,"comp":"WBC"},{"medal":"Bronze","beer":"Steenbrugge Tripel","brewery":"Palm Breweries","style":"Belgian-Style Tripel","year":2012,"comp":"WBC"},{"medal":"Silver","beer":"Nectar des Dieux","brewery":"Bastone Brewery","style":"Belgian-Style Tripel","year":2012,"comp":"WBC"},{"medal":"Gold","beer":"Westmalle Trappist Tripel","brewery":"Westmalle Trappist Brewery","style":"Belgian-Style Tripel","year":2012,"comp":"WBC"},{"medal":"Bronze","beer":"Prisoner of Hell","brewery":"Dock Street Brewery","style":"Belgian-Style Pale Strong Ale","year":2012,"comp":"WBC"},{"medal":"Silver","beer":"Thor's Hammer","brewery":"Bastone Brewery","style":"Belgian-Style Pale Strong Ale","year":2012,"comp":"WBC"},{"medal":"Gold","beer":"Piraat","brewery":"Van Steenberge","style":"Belgian-Style Pale Strong Ale","year":2012,"comp":"WBC"},{"medal":"Bronze","beer":"Grand Prestige","brewery":"Hertog Jan Brouwerij","style":"Belgian-Style Dark Strong Ale","year":2012,"comp":"WBC"},{"medal":"Silver","beer":"Two Tortugas Belgian Quad","brewery":"Karl Strauss Brewing Co.","style":"Belgian-Style Dark Strong Ale","year":2012,"comp":"WBC"},{"medal":"Gold","beer":"Batch 333: The Velvet Fog","brewery":"Sun King Brewing Co.","style":"Belgian-Style Dark Strong Ale","year":2012,"comp":"WBC"},{"medal":"Bronze","beer":"Rhinoceros","brewery":"Telegraph Brewing Co.","style":"Other Belgian-Style Ale","year":2012,"comp":"WBC"},{"medal":"Silver","beer":"Gauloise Amber","brewery":"Brasserie du Bocq","style":"Other Belgian-Style Ale","year":2012,"comp":"WBC"},{"medal":"Gold","beer":"Seef","brewery":"Antwerpse Brouw Compagnie","style":"Other Belgian-Style Ale","year":2012,"comp":"WBC"},{"medal":"Bronze","beer":"Mother Lode Golden Ale","brewery":"Laurelwood Brewing Co.","style":"English-Style Summer Ale","year":2012,"comp":"WBC"},{"medal":"Silver","beer":"Stone & Wood Pacific Ale","brewery":"Stone & Wood Brewing Co.","style":"English-Style Summer Ale","year":2012,"comp":"WBC"},{"medal":"Gold","beer":"Cross of Gold","brewery":"Revolution Brewing","style":"English-Style Summer Ale","year":2012,"comp":"WBC"},{"medal":"Bronze","beer":"Caldera Ashland Amber","brewery":"Caldera Brewing Co.","style":"Classic English-Style Pale Ale","year":2012,"comp":"WBC"},{"medal":"Silver","beer":"Summit Extra Pale Ale","brewery":"Summit Brewing Co.","style":"Classic English-Style Pale Ale","year":2012,"comp":"WBC"},{"medal":"Gold","beer":"Annadel Pale Ale","brewery":"Third Street Aleworks","style":"Classic English-Style Pale Ale","year":2012,"comp":"WBC"},{"medal":"Bronze","beer":"Intercontinental Pale Ale","brewery":"Flossmoor Station Brewing Co.","style":"English-Style India Pale Ale","year":2012,"comp":"WBC"},{"medal":"Silver","beer":"IP'Eh!","brewery":"Russell Brewing Co.","style":"English-Style India Pale Ale","year":2012,"comp":"WBC"},{"medal":"Gold","beer":"Man Beer","brewery":"Bull & Bush Brewery","style":"English-Style India Pale Ale","year":2012,"comp":"WBC"},{"medal":"Bronze","beer":"8th Street Ale","brewery":"Four Peaks Brewing Co.","style":"Ordinary or Special Bitter","year":2012,"comp":"WBC"},{"medal":"Silver","beer":"Happy Hour Hero Ale","brewery":"Montana Brewing Co.","style":"Ordinary or Special Bitter","year":2012,"comp":"WBC"},{"medal":"Gold","beer":"Redoak Bitter","brewery":"Redoak","style":"Ordinary or Special Bitter","year":2012,"comp":"WBC"},{"medal":"Bronze","beer":"The Tower E.S.B.","brewery":"Bull & Bush Brewery","style":"Extra Special Bitter","year":2012,"comp":"WBC"},{"medal":"Silver","beer":"GAR Pale Ale","brewery":"Great American Restaurants","style":"Extra Special Bitter","year":2012,"comp":"WBC"},{"medal":"Gold","beer":"Red Betty","brewery":"Central City Brewing Co.","style":"Extra Special Bitter","year":2012,"comp":"WBC"},{"medal":"Bronze","beer":"Beltaine Scottish Ale","brewery":"Shoreline Brewery","style":"Scottish-Style Ale","year":2012,"comp":"WBC"},{"medal":"Silver","beer":"Redhawk Ale","brewery":"Rockyard Brewing Company","style":"Scottish-Style Ale","year":2012,"comp":"WBC"},{"medal":"Gold","beer":"MacPelican's Scottish Style Ale","brewery":"Pelican Pub & Brewery","style":"Scottish-Style Ale","year":2012,"comp":"WBC"},{"medal":"Bronze","beer":"Nerf Herder","brewery":"Pizza Port San Clemente","style":"English-Style Mild Ale","year":2012,"comp":"WBC"},{"medal":"Silver","beer":"Alyssa's Attitude","brewery":"Oggi's Pizza & Brewing Co.","style":"English-Style Mild Ale","year":2012,"comp":"WBC"},{"medal":"Gold","beer":"Crown Brown","brewery":"Crown Brewing","style":"English-Style Mild Ale","year":2012,"comp":"WBC"},{"medal":"Bronze","beer":"Sweet George's Brown","brewery":"Dillon DAM Brewery","style":"English-Style Brown Ale","year":2012,"comp":"WBC"},{"medal":"Silver","beer":"Nut Brown Ale","brewery":"Redhook Ale Brewery","style":"English-Style Brown Ale","year":2012,"comp":"WBC"},{"medal":"Gold","beer":"Longboard Brown Ale","brewery":"Rock Bottom La Jolla","style":"English-Style Brown Ale","year":2012,"comp":"WBC"},{"medal":"Bronze","beer":"Chocolate Porter","brewery":"Bayhawk Ales","style":"Brown Porter","year":2012,"comp":"WBC"},{"medal":"Silver","beer":"Poundage Porter","brewery":"Sound Brewery","style":"Brown Porter","year":2012,"comp":"WBC"},{"medal":"Gold","beer":"Double Nut Brown","brewery":"Mammoth Brewing Co.","style":"Brown Porter","year":2012,"comp":"WBC"},{"medal":"Bronze","beer":"Chocolate Porter","brewery":"Kumazawa Brewing Co.","style":"Robust Porter","year":2012,"comp":"WBC"},{"medal":"Silver","beer":"Pro-Am Porter","brewery":"Wormtown Brewery","style":"Robust Porter","year":2012,"comp":"WBC"},{"medal":"Gold","beer":"Pier Rat Porter","brewery":"Pizza Port San Clemente","style":"Robust Porter","year":2012,"comp":"WBC"},{"medal":"Bronze","beer":"Blackjack Stout","brewery":"Feather Falls Casino Brewing Co.","style":"Sweet Stout","year":2012,"comp":"WBC"},{"medal":"Silver","beer":"Outlaw Oatmeal Stout","brewery":"Great Basin Brewing Co.","style":"Sweet Stout","year":2012,"comp":"WBC"},{"medal":"Gold","beer":"Steel Toe Stout","brewery":"Ska Brewing Co.","style":"Sweet Stout","year":2012,"comp":"WBC"},{"medal":"Bronze","beer":"Alaskan Oatmeal Stout","brewery":"Alaskan Brewing Co.","style":"Oatmeal Stout","year":2012,"comp":"WBC"},{"medal":"Silver","beer":"Stumblers Stout","brewery":"Columbia River Brewing Co.","style":"Oatmeal Stout","year":2012,"comp":"WBC"},{"medal":"Gold","beer":"Naked Oat Stout","brewery":"Rock Bottom College Park","style":"Oatmeal Stout","year":2012,"comp":"WBC"},{"medal":"Bronze","beer":"Cold Smoke Scotch Ale","brewery":"Kettlehouse Brewing Co.","style":"Scotch Ale","year":2012,"comp":"WBC"},{"medal":"Silver","beer":"Way Heavy","brewery":"Pizza Port San Clemente","style":"Scotch Ale","year":2012,"comp":"WBC"},{"medal":"Gold","beer":"Wee Heavy","brewery":"Dry Dock Brewing Co.","style":"Scotch Ale","year":2012,"comp":"WBC"},{"medal":"Bronze","beer":"Brooklyn Black Chocolate Stout","brewery":"The Brooklyn Brewery","style":"British-Style Imperial Stout","year":2012,"comp":"WBC"},{"medal":"Silver","beer":"Luscious","brewery":"The Alchemist","style":"British-Style Imperial Stout","year":2012,"comp":"WBC"},{"medal":"Gold","beer":"Russian Imperial Stout","brewery":"Iron Hill Brewery & Restaurant - Media","style":"British-Style Imperial Stout","year":2012,"comp":"WBC"},{"medal":"Bronze","beer":"Old Scrooge","brewery":"Silver City Brewery","style":"Old Ale or Strong Ale","year":2012,"comp":"WBC"},{"medal":"Silver","beer":"AleSmith Decadence 2010 Old Ale","brewery":"AleSmith Brewing Co.","style":"Old Ale or Strong Ale","year":2012,"comp":"WBC"},{"medal":"Gold","beer":"Old Ale","brewery":"Iron Hill Brewery & Restaurant - Media","style":"Old Ale or Strong Ale","year":2012,"comp":"WBC"},{"medal":"Bronze","beer":"AleSmith Old Numbskull","brewery":"AleSmith Brewing Co.","style":"Barley Wine-Style Ale","year":2012,"comp":"WBC"},{"medal":"Silver","beer":"Barley's Wine","brewery":"La Cumbre Brewing Co.","style":"Barley Wine-Style Ale","year":2012,"comp":"WBC"},{"medal":"Gold","beer":"Stormwatcher's Winterfest","brewery":"Pelican Pub & Brewery","style":"Barley Wine-Style Ale","year":2012,"comp":"WBC"},{"medal":"Bronze","beer":"McLovin","brewery":"Vintage Brewing Co.","style":"Irish-Style Red Ale","year":2012,"comp":"WBC"},{"medal":"Silver","beer":"Alaskan Amber","brewery":"Alaskan Brewing Co.","style":"Irish-Style Red Ale","year":2012,"comp":"WBC"},{"medal":"Gold","beer":"Red Trolley Ale","brewery":"Karl Strauss Brewing Co.","style":"Irish-Style Red Ale","year":2012,"comp":"WBC"},{"medal":"Bronze","beer":"Breakside Dry Stout","brewery":"Breakside Brewery","style":"Classic Irish-Style Dry Stout","year":2012,"comp":"WBC"},{"medal":"Silver","beer":"Ring of Dingle","brewery":"Sun King Brewing Co.","style":"Classic Irish-Style Dry Stout","year":2012,"comp":"WBC"},{"medal":"Gold","beer":"Blarney Sisters Dry Irish Stout","brewery":"Third Street Aleworks","style":"Classic Irish-Style Dry Stout","year":2012,"comp":"WBC"},{"medal":"Bronze","beer":"Voo Doo","brewery":"Left Coast Brewing Co.","style":"Foreign-Style Stout","year":2012,"comp":"WBC"},{"medal":"Silver","beer":"Malpais Stout","brewery":"La Cumbre Brewing Co.","style":"Foreign-Style Stout","year":2012,"comp":"WBC"},{"medal":"Gold","beer":"Starry Night Stout","brewery":"Island Brewing Co.","style":"Foreign-Style Stout","year":2012,"comp":"WBC"},{"medal":"Bronze","beer":"Steelhead Extra Pale","brewery":"Mad River Brewing Co.","style":"Golden or Blonde Ale","year":2012,"comp":"WBC"},{"medal":"Silver","beer":"Labatt 50","brewery":"Labatt Brewing Co.","style":"Golden or Blonde Ale","year":2012,"comp":"WBC"},{"medal":"Gold","beer":"Foam Top","brewery":"Beachwood BBQ & Brewing","style":"Golden or Blonde Ale","year":2012,"comp":"WBC"},{"medal":"Bronze","beer":"BrickStone APA","brewery":"BrickStone Restaurant & Brewery","style":"American-Style Pale Ale","year":2012,"comp":"WBC"},{"medal":"Silver","beer":"Mission Street Pale","brewery":"Firestone Walker Brewing Co.","style":"American-Style Pale Ale","year":2012,"comp":"WBC"},{"medal":"Gold","beer":"Pale 31","brewery":"Firestone Walker Brewing Co.","style":"American-Style Pale Ale","year":2012,"comp":"WBC"},{"medal":"Bronze","beer":"Alaskan IPA","brewery":"Alaskan Brewing Co.","style":"American-Style Strong Pale Ale","year":2012,"comp":"WBC"},{"medal":"Silver","beer":"Odell IPA","brewery":"Odell Brewing Co.","style":"American-Style Strong Pale Ale","year":2012,"comp":"WBC"},{"medal":"Gold","beer":"Hop Knot","brewery":"Four Peaks Brewing Co.","style":"American-Style Strong Pale Ale","year":2012,"comp":"WBC"},{"medal":"Bronze","beer":"Elevated IPA","brewery":"La Cumbre Brewing Co.","style":"American-Style India Pale Ale","year":2012,"comp":"WBC"},{"medal":"Silver","beer":"Head Hunter IPA","brewery":"Fat Heads Brewery","style":"American-Style India Pale Ale","year":2012,"comp":"WBC"},{"medal":"Gold","beer":"DRIPA","brewery":"Kuhnhenn Brewing Co.","style":"American-Style India Pale Ale","year":2012,"comp":"WBC"},{"medal":"Bronze","beer":"Palate Wrecker","brewery":"Green Flash Brewing Co.","style":"Imperial India Pale Ale","year":2012,"comp":"WBC"},{"medal":"Silver","beer":"Saint Arnold Endeavour","brewery":"Saint Arnold Brewing Co.","style":"Imperial India Pale Ale","year":2012,"comp":"WBC"},{"medal":"Gold","beer":"Poor Man's IPA","brewery":"Pizza Port Carlsbad","style":"Imperial India Pale Ale","year":2012,"comp":"WBC"},{"medal":"Bronze","beer":"Mavericks Amber Ale","brewery":"Half Moon Bay Brewing Co.","style":"American-Style Amber\/Red Ale","year":2012,"comp":"WBC"},{"medal":"Silver","beer":"Swan Lake Beer Amber Swan Ale","brewery":"Hyokoyashikinomori Brewery Tenchokaku Co.","style":"American-Style Amber\/Red Ale","year":2012,"comp":"WBC"},{"medal":"Gold","beer":"Big Cottonwood","brewery":"Utah Brewers Co-op","style":"American-Style Amber\/Red Ale","year":2012,"comp":"WBC"},{"medal":"Bronze","beer":"Pursuit of Hopiness","brewery":"Grand Teton Brewing Co.","style":"Imperial Red Ale","year":2012,"comp":"WBC"},{"medal":"Silver","beer":"Bigfoot","brewery":"Sierra Nevada Brewing Co.","style":"Imperial Red Ale","year":2012,"comp":"WBC"},{"medal":"Gold","beer":"G'Knight Imperial Red Ale","brewery":"Oskar Blues Brewery","style":"Imperial Red Ale","year":2012,"comp":"WBC"},{"medal":"Bronze","beer":"Great American Brown","brewery":"Pizza Port Carlsbad","style":"American-Style Brown Ale","year":2012,"comp":"WBC"},{"medal":"Silver","beer":"Uptown Brown","brewery":"Galena Brewing Co.","style":"American-Style Brown Ale","year":2012,"comp":"WBC"},{"medal":"Gold","beer":"Face Down Brown","brewery":"Telluride Brewing Co.","style":"American-Style Brown Ale","year":2012,"comp":"WBC"},{"medal":"Bronze","beer":"Raven","brewery":"Thornbridge","style":"American-Style Black Ale","year":2012,"comp":"WBC"},{"medal":"Silver","beer":"Tarantulas 2.0","brewery":"Pizza Port Ocean Beach","style":"American-Style Black Ale","year":2012,"comp":"WBC"},{"medal":"Gold","beer":"Black Racer","brewery":"Bear Republic Brewing Co.","style":"American-Style Black Ale","year":2012,"comp":"WBC"},{"medal":"Bronze","beer":"Achievement Beyond Life's Experiences American Stout Brit Antrim Benefit Beer","brewery":"Pizza Port Ocean Beach","style":"American-Style Stout","year":2012,"comp":"WBC"},{"medal":"Silver","beer":"Pike XXXXX Extra Stout","brewery":"Pike Brewing Co.","style":"American-Style Stout","year":2012,"comp":"WBC"},{"medal":"Gold","beer":"Rise American Stout","brewery":"Revolution Brewing","style":"American-Style Stout","year":2012,"comp":"WBC"},{"medal":"Bronze","beer":"Imperial Stout","brewery":"Olde Hickory Brewery","style":"American-Style Imperial Stout","year":2012,"comp":"WBC"},{"medal":"Silver","beer":"The Fundamental Blackhorn","brewery":"Hornbeer","style":"American-Style Imperial Stout","year":2012,"comp":"WBC"},{"medal":"Gold","beer":"Imperial Stout","brewery":"Silver City Brewery","style":"American-Style Imperial Stout","year":2012,"comp":"WBC"}]